LICENSE
MANIFEST.in
README.md
setup.py
django_paymentsos/__init__.py
django_paymentsos/admin.py
django_paymentsos/apps.py
django_paymentsos/enumerators.py
django_paymentsos/fields.py
django_paymentsos/forms.py
django_paymentsos/models.py
django_paymentsos/settings.py
django_paymentsos/signals.py
django_paymentsos/tests.py
django_paymentsos/urls.py
django_paymentsos/utils.py
django_paymentsos/views.py
django_paymentsos.egg-info/PKG-INFO
django_paymentsos.egg-info/SOURCES.txt
django_paymentsos.egg-info/dependency_links.txt
django_paymentsos.egg-info/not-zip-safe
django_paymentsos.egg-info/requires.txt
django_paymentsos.egg-info/top_level.txt
django_paymentsos/migrations/0001_initial.py
django_paymentsos/migrations/0002_paymentsosnotification_sub_category.py
django_paymentsos/migrations/0003_auto_20181216_1147.py
django_paymentsos/migrations/0004_auto_20181216_1834.py
django_paymentsos/migrations/__init__.py
docs/changelog.rst